setup.cfg
setup.py
pysimu/__init__.py
pysimu/pysimu.py
pysimu.egg-info/PKG-INFO
pysimu.egg-info/SOURCES.txt
pysimu.egg-info/dependency_links.txt
pysimu.egg-info/requires.txt
pysimu.egg-info/top_level.txt