Metadata-Version: 1.1
Name: pysimu
Version: 0.0.1e
Summary: Simulations tools
Home-page: https://github.com/jmmauricio/pysimu.git
Author: Juan Manuel Mauricio
Author-email: jmmauricio6@gmail.com
License: MIT
Download-URL: https://github.com/jmmauricio/pysimu/tarball/0.1
Keywords: dynamics model simulation
Platform: UNKNOWN
Classifier: Development Status :: 3 - Alpha
Classifier: Topic :: Utilities
Classifier: License :: OSI Approved :: BSD License
